MANIFEST.in
README.md
setup.py
django_bootstrapper/__init__.py
django_bootstrapper/conf.py
django_bootstrapper/django_bootstrapper.py
django_bootstrapper.egg-info/PKG-INFO
django_bootstrapper.egg-info/SOURCES.txt
django_bootstrapper.egg-info/dependency_links.txt
django_bootstrapper.egg-info/not-zip-safe
django_bootstrapper.egg-info/requires.txt
django_bootstrapper.egg-info/top_level.txt
django_bootstrapper/bin/django-bootstrapper.py
django_bootstrapper/templates/.gitignore.tmpl
django_bootstrapper/templates/README.md.tmpl
django_bootstrapper/templates/docker_config/.dockerignore.tmpl
django_bootstrapper/templates/docker_config/Dockerfile.tmpl
django_bootstrapper/templates/docker_config/requirements.txt.tmpl
django_bootstrapper/templates/docker_config/uwsgi.ini.tmpl
django_bootstrapper/templates/project_config/settings_prod.py.tmpl
django_bootstrapper/templates/scripts/create_bucket.sh.tmpl
django_bootstrapper/templates/scripts/create_database.sql.tmpl