Metadata-Version: 2.1
Name: django-bootstrapper
Version: 0.1.3
Summary: A simple bootstrapper for django applications
Home-page: http://github.com/contraslash/django-bootstrapper
Author: contraslash S.A.S.
Author-email: ma0@contraslash.com
License: MIT
Project-URL: Bug Reports, https://github.com/contraslash/django-bootstrapper/issues
Project-URL: Source, https://github.com/contraslash/django-bootstrapper
Project-URL: Contraslash, https://contraslash.com/
Keywords: django bootstrapping tool
Platform: UNKNOWN
Classifier: Development Status :: 3 - Alpha
Classifier: Intended Audience :: Developers
Classifier: License :: OSI Approved :: MIT License
Classifier: Programming Language :: Python :: 3
